blogist/__init__.py
blogist/gist.py
blogist/types.py
blogist-0.0.2.dist-info/METADATA
blogist-0.0.2.dist-info/RECORD
blogist-0.0.2.dist-info/WHEEL
blogist-0.0.2.dist-info/entry_points.txt
blogist-0.0.2.dist-info/top_level.txt
