Metadata-Version: 2.1
Name: blogist
Version: 0.0.2
Summary: a tool to get user's blog posts from GitHub Gist
Home-page: https://github.com/kemingy/blogist
Author: keming
Author-email: kemingy94@gmail.com
License: UNKNOWN
Platform: UNKNOWN
Classifier: Programming Language :: Python :: 3.7
Requires-Python: >=3.7
Requires-Dist: requests (>=2.0)
